<LinuxCNC-Features>
  <feature old-selected="False" src="/home/fernand/linuxcnc-features/ini/fv_task.ini" expanded="True" help="&lt;b&gt;Create Task&lt;/b&gt;" name="Task" o-name="Task" image="group.png" after="&#10;(end items added)&#10;&#9;o&lt;#self_id-unmount&gt; if [#param_umnt]&#10;&#9;&#9;T0&#10;&#9;o&lt;#self_id-unmount&gt; endif&#10;&#10;&#9;o&lt;#self_id-setposition&gt; if [#param_sp]&#10;&#9;&#9;G0 Z[#param_pz]&#10;&#9;&#9;G0 X[#param_px] Y[#param_py]&#10;&#9;o&lt;#self_id-setposition&gt; endif&#10;o&lt;#self_id-enabled&gt; endif" order="['PARAM_ENA', 'PARAM_H1', 'PARAM_SURF', 'PARAM_DEPTH', 'PARAM_Z_CLEAR', 'PARAM_FCUT', 'PARAM_H3', 'PARAM_CP1', 'PARAM_CP2', 'PARAM_CP3', 'PARAM_CP4', 'PARAM_CP5', 'PARAM_ITM', 'PARAM_H2', 'PARAM_UMNT', 'PARAM_SP', 'PARAM_PX', 'PARAM_PY', 'PARAM_PZ']" new-selected="False" path="0" call="" definitions="" icon="group.png" type="task" id="task-001" before="&#10;o&lt;#self_id-enabled&gt; if [#param_ena]&#10;&#9;#&lt;_surface&gt; = #param_surf&#10;&#9;#&lt;_depth&gt; = #param_depth&#10;&#9;#&lt;_z_clear&gt; = #param_z_clear&#10;&#9;#&lt;_show_final_cuts&gt; = #param_fcut&#10;&#10;&#9;(custom params)&#10;&#9;#param_cp1&#10;&#9;#param_cp2&#10;&#9;#param_cp3&#10;&#9;#param_cp4&#10;&#9;#param_cp5&#10;&#9;(end custom params)&#10;&#10;(begin items added)&#10;">
    <param tool_tip="Disabling will also disable ALL items" name="Enabled" value="1" call="#param_ena" path="0:0" type="bool"/>
    <param tool_tip="Milling" type="sub-header" call="#param_h1" name="Milling" path="0:1"/>
    <param tool_tip="Surface" name="Cut start" value="0.000" header="h1" call="#param_surf" path="0:1:0" type="float" icon="surface.png"/>
    <param tool_tip="Must be lower then cut start" name="Cut down to" metric_value="-15" value="-15.000" header="h1" call="#param_depth" path="0:1:1" type="float" icon="depth.png"/>
    <param tool_tip="Z height to clear work piece" name="Clear Height" metric_value="1.5" value="1.500" header="h1" call="#param_z_clear" path="0:1:2" type="float" icon="rappid.png"/>
    <param tool_tip="Preview ALL checked items final cuts" name="Preview final cuts" value="1" header="h1" call="#param_fcut" path="0:1:3" type="bool"/>
    <param tool_tip="Enter as gcode" type="sub-header" call="#param_h3" name="Custom" path="0:2"/>
    <param tool_tip="Enter param as custom GCode" name="Param 1" value="" header="h3" call="#param_cp1" path="0:2:0" type="string" icon="gcode.png"/>
    <param tool_tip="Enter param as custom GCode" name="Param 2" value="" header="h3" call="#param_cp2" path="0:2:1" type="string" icon="gcode.png"/>
    <param tool_tip="Enter param as custom GCode" name="Param 3" value="" header="h3" call="#param_cp3" path="0:2:2" type="string" icon="gcode.png"/>
    <param tool_tip="Enter param as custom GCode" name="Param 4" value="" header="h3" call="#param_cp4" path="0:2:3" type="string" icon="gcode.png"/>
    <param tool_tip="Enter param as custom GCode" name="Param 5" value="" header="h3" call="#param_cp5" path="0:2:4" type="string" icon="gcode.png"/>
    <param tool_tip="Add subroutines here" name="Items" old-selected="False" expanded="True" new-selected="False" call="#param_itm" path="0:3" type="items" icon="items.png">
      <feature old-selected="False" src="/home/fernand/linuxcnc-features/ini/fv_drill-change.ini" after="" help="&lt;b&gt;Add drill change gcode&lt;/b&gt;&#10;Changes setting accordingly" o-name="Drill Change" before="" image="tool-change.png" expanded="False" id="drillchng-001" new-selected="False" definitions="" call="&#10;(Drill change)&#10;&#9;o&lt;#self_id-ena&gt; if [#param_ena]&#10;&#9;&#9;o&lt;#self_id-stopcooling&gt; if [#param_stop]&#10;&#9;&#9;&#9;M9&#10;&#9;&#9;o&lt;#self_id-stopcooling&gt; endif&#10;&#9;&#9;T#param_n M6 G43&#10;&#10;&#9;&#9;o&lt;#self_id-if&gt; if [#&lt;_tool_probe_set&gt;]&#10;&#9;&#9;&#9;o&lt;set-tool-length&gt; CALL&#10;&#9;&#9;o&lt;#self_id-if&gt; endif&#10;&#10;&#9; &#9;M#param_dir&#10;&#9;&#9;M#param_cool&#10;&#9;o&lt;#self_id-ena&gt; endif&#10;&#10;S#param_speed&#10;F#param_feed&#10;&#10;#&lt;_drill_feed&gt; = #param_feed&#10;#&lt;_drill_retract&gt; = #param_r&#10;#&lt;_drill_mode&gt; = #param_dm&#10;#&lt;_drill_dwell&gt; = #param_d&#10;#&lt;_drill_q&gt; = #param_q&#10;(End drill change)&#10;" path="0:3:0" icon="tool-change.png" type="drillchng" order="['PARAM_ENA', 'PARAM_H1', 'PARAM_N', 'PARAM_STOP', 'PARAM_COOL', 'PARAM_DIR', 'PARAM_H2', 'PARAM_H4', 'PARAM_SPEED', 'PARAM_FEED', 'PARAM_H3', 'PARAM_DM', 'PARAM_R', 'PARAM_D', 'PARAM_Q']" name="Drill Change">
        <param tool_tip="Enabled" name="Enabled" value="1" call="#param_ena" path="0:3:0:0" type="bool"/>
        <param tool_tip="Drill, execution" call="#param_h1" type="sub-header" name="Drill, execution" path="0:3:0:1"/>
        <param tool_tip="Drill number from table" name="Number" value="0" header="h1" call="#param_n" path="0:3:0:1:0" minimum_value="0" type="int" icon="num.png"/>
        <param tool_tip="Stop cooling before changing drill" name="Stop cooling" value="1" header="h1" call="#param_stop" path="0:3:0:1:1" type="bool" icon=""/>
        <param tool_tip="Use flood, mist or none" name="Re-start cooling" value="9" header="h1" call="#param_cool" path="0:3:0:1:2" type="combo" options="None=9:Flood=8:Mist=7" icon=""/>
        <param tool_tip="Select tool rotation" name="Spindle direction" value="3" header="h1" call="#param_dir" path="0:3:0:1:3" type="combo" options="Clockwise=3:Counterclockwise=4" icon="cw-ccw.png"/>
        <param tool_tip="Drilling" call="#param_h2" type="sub-header" name="Drilling" path="0:3:0:2"/>
        <param tool_tip="Speed and feed" name="Speed and feed" header="h2" call="#param_h4" path="0:3:0:2:0" type="sub-header"/>
        <param tool_tip="Set spindle speed" name="Spindle speed" value="1000" header="h4" call="#param_speed" path="0:3:0:2:0:0" minimum_value="0" type="int" icon="tool-spindle.png"/>
        <param tool_tip="Set feed" name="Drilling feed" metric_value="25" value="25.000" header="h4" call="#param_feed" path="0:3:0:2:0:1" type="float" icon="tool-vertical-feed.png"/>
        <param tool_tip="Mode" name="Mode" header="h2" call="#param_h3" path="0:3:0:2:1" type="sub-header"/>
        <param tool_tip="G73 requires Q&gt;0 and R&#10;G81 requires R&#10;G82 requires R and P&#10;G83 requires Q&gt;0 and R" name="Drilling mode" value="73" header="h3" call="#param_dm" path="0:3:0:2:1:0" type="combo" options="With Chip Breaking - G73=73:Standard - G81=81:Dwell at the bottom - G82=82:Peck Drilling Cycle - G83=83" icon=""/>
        <param tool_tip="Retract height" name="Retract (R)" metric_value="2.5" value="2.500" header="h3" call="#param_r" path="0:3:0:2:1:1" type="float" icon=""/>
        <param tool_tip="Dwell seconds" name="Dwell (P)" value="3.000" header="h3" call="#param_d" path="0:3:0:2:1:2" type="float" icon=""/>
        <param tool_tip="" name="Delta (Q)" value="0.100" header="h3" call="#param_q" path="0:3:0:2:1:3" minimum_value="0.01" type="float" icon=""/>
      </feature>
      <feature old-selected="True" src="/home/fernand/linuxcnc-features/ini/mill/fv_rectangular-array.ini" expanded="False" help="&lt;b&gt;Create a rectangular array of items&lt;/b&gt;" name="Array Rect" o-name="Array Rect" image="rect-array.png" after="&#10;&#9;&#9;&#9;(End array items)&#10;&#10;&#9;&#9;&#9;(No Angular increment in Y axis)&#10;&#9;&#9;&#9;#&lt;#self_id-Yy&gt; = [#&lt;#self_id-Yy&gt; + #param_dy]&#10;&#9;&#9;O&lt;#self_id-Y&gt; END REPEAT&#10;&#10;&#9;&#9;O&lt;coordinate-sys-to-num&gt; CALL [#param_coord]&#10;&#9;&#9;#&lt;coord&gt; = #&lt;_coordinate-to-num&gt;&#10;&#9;&#9;G10 L2 P[#&lt;Ycoord&gt;] X[#&lt;#self_id-Yx0&gt; - #param_x] Y[#&lt;#self_id-Yy0&gt; - #param_y] R[#&lt;#self_id-Yr0&gt;]&#10;&#9;&#9;O&lt;coordinate-sys-from-num&gt; CALL [#&lt;#self_id-Yrest-coord&gt;]&#10;&#9;&#9;G[#&lt;_coordinate-from-num&gt;]&#10;&#10;&#9;&#9;#&lt;#self_id-Xx&gt; = [#&lt;#self_id-Xx&gt; + #param_dx]&#10;&#9;O&lt;#self_id&gt; END REPEAT&#9;(End Y axis and return to main loop)&#10;&#10;&#9;O&lt;coordinate-sys-to-num&gt; CALL [#param_coord]&#10;&#9;#&lt;coord&gt; = #&lt;_coordinate-to-num&gt;&#10;&#9;G10 L2 P[#&lt;coord&gt;] X[#&lt;#self_id-Xx0&gt; - #param_x] Y[#&lt;#self_id-Xy0&gt; - #param_y] R[#&lt;#self_id-Xr0&gt; - #param_r]&#10;&#9;O&lt;coordinate-sys-from-num&gt; CALL [#&lt;#self_id-Xrest-coord&gt;]&#10;&#9;G[#&lt;_coordinate-from-num&gt;]&#10;O&lt;#self_id-enabled&gt; endif&#10;(End Rectangular Array)" order="['PARAM_ENA', 'PARAM_H1', 'PARAM_OPT', 'PARAM_X', 'PARAM_Y', 'PARAM_H5', 'PARAM_NUMX', 'PARAM_NUMY', 'PARAM_H2', 'PARAM_DX', 'PARAM_DY', 'PARAM_H3', 'PARAM_R', 'PARAM_H4', 'PARAM_COORD', 'PARAM_ITEMS']" new-selected="False" path="0:3:1" call="" definitions="" icon="rect-array.png" type="array-rect" id="array-rect-001" before="&#10;(Rectangular Array)&#10;O&lt;#self_id-enabled&gt; if [#param_ena]&#10;&#10;&#9;(Get x,y,r in machine coordinates)&#10;&#9;O&lt;#self_id-opt&gt; if [#param_opt EQ 1] ;center of array&#10;&#9;&#9;#&lt;#self_id-cx&gt; = [[#param_numx - 1] * #param_dx / 2]&#10;&#9;&#9;#&lt;#self_id-cy&gt; = [[#param_numy - 1] * #param_dy / 2]&#10;&#9;&#9;O&lt;#self_id-opt&gt; else ;align on low XY&#10;&#9;&#9;#&lt;#self_id-cx&gt; = 0&#10;&#9;&#9;#&lt;#self_id-cy&gt; = 0&#10;&#9;O&lt;#self_id-opt&gt; endif&#10;&#10;&#9;O&lt;get-offsets&gt; CALL&#10;&#9;#&lt;#self_id-Xx&gt; = 0&#10;&#10;&#9;#&lt;#self_id-Xx0&gt; = [#&lt;_get_offsets_x&gt; - #&lt;#self_id-cx&gt; + #param_x]&#10;&#9;#&lt;#self_id-Xy0&gt; = [#&lt;_get_offsets_y&gt; - #&lt;#self_id-cy&gt;]&#10;&#9;#&lt;#self_id-Xr0&gt; = [#&lt;_get_offsets_r&gt; + #param_r]&#10;&#10;&#9;#&lt;#self_id-Xrest-coord&gt; = #5220&#10;&#9;G[#param_coord]&#10;&#10;&#9;(Loop X axis)&#10;&#9;O&lt;#self_id&gt; REPEAT [#param_numx]&#10;&#10;&#9;&#9;G92.1 (disable G92 offsets - they ruin the array after rotating coordinates)&#10;&#9;&#9;(move and rotate coordinates)&#10;&#10;&#9;&#9;O&lt;coordinate-sys-to-num&gt; CALL [#param_coord]&#10;&#9;&#9;#&lt;#self_id-coord&gt; = #&lt;_coordinate-to-num&gt;&#10;&#10;&#9;&#9;(Get rotated coordinates)&#10;&#9;&#9;O&lt;rotate-xy&gt; CALL [#&lt;#self_id-Xx&gt; + #&lt;#self_id-Xx0&gt;] [#&lt;#self_id-Xy0&gt;] [#&lt;#self_id-Xx0&gt; + #&lt;#self_id-cx&gt;] [#&lt;#self_id-Xy0&gt; + #&lt;#self_id-cy&gt;] [#&lt;#self_id-Xr0&gt;]&#10;&#10;&#9;&#9;G10 L2 P[#&lt;#self_id-coord&gt;] X#&lt;_rotate_result_x&gt; Y#&lt;_rotate_result_y&gt; R[#&lt;#self_id-Xr0&gt;]&#10;&#10;&#9;&#9;(Array body Y axis)&#10;&#9;&#9;(Get x,y,r in machine coordinates)&#10;&#9;&#9;O&lt;get-offsets&gt; CALL&#10;&#9;&#9;#&lt;#self_id-Yy&gt; = [0]&#10;&#10;&#9;&#9;#&lt;#self_id-Yx0&gt; = [#&lt;_get_offsets_x&gt;]&#10;&#9;&#9;#&lt;#self_id-Yy0&gt; = [#&lt;_get_offsets_y&gt; + #param_y]&#10;&#9;&#9;#&lt;#self_id-Yr0&gt; = [#&lt;_get_offsets_r&gt;]&#10;&#9;&#9;#&lt;#self_id-Yrest-coord&gt; = #5220&#10;&#10;&#9;&#9;G[#param_coord]&#10;&#10;&#9;&#9;(Loop Y axis)&#10;&#9;&#9;O&lt;#self_id-Y&gt; REPEAT [#param_numy]&#10;&#10;&#9;&#9;&#9;G92.1 (disable G92 offsets - they ruin the array after rotating coordinates)&#10;&#9;&#9;&#9;(move and rotate coordinates)&#10;&#10;&#9;&#9;&#9;O&lt;coordinate-sys-to-num&gt; CALL [#param_coord]&#10;&#9;&#9;&#9;#&lt;Ycoord&gt; = #&lt;_coordinate-to-num&gt;&#10;&#10;&#9;&#9;&#9;(Get rotated coordinates)&#10;&#9;&#9;&#9;O&lt;rotate-xy&gt; CALL [#&lt;#self_id-Yx0&gt;] [#&lt;#self_id-Yy&gt; + #&lt;#self_id-Yy0&gt;] [#&lt;#self_id-Yx0&gt;] [#&lt;#self_id-Yy0&gt;] [#&lt;#self_id-Yr0&gt;]&#10;&#10;&#9;&#9;&#9;G10 L2 P[#&lt;Ycoord&gt;] X#&lt;_rotate_result_x&gt; Y#&lt;_rotate_result_y&gt; R[#&lt;#self_id-Yr0&gt;]&#10;&#10;&#9;&#9;&#9;(Array items ...)&#10;">
        <param tool_tip="Disabling will disable ALL items" name="Enabled" value="1" call="#param_ena" path="0:3:1:0" type="bool"/>
        <param tool_tip="Origin" type="sub-header" call="#param_h1" name="Coords" path="0:3:1:1"/>
        <param tool_tip="Select options" name="Position option" value="0" header="h1" call="#param_opt" path="0:3:1:1:0" type="combo" options="Low XY position=0:Center of array=1" icon="diameter.png"/>
        <param tool_tip="Origin X" name="X" value="0.000" header="h1" call="#param_x" path="0:3:1:1:1" type="float" icon="x.png"/>
        <param tool_tip="Origin Y" name="Y" value="0.000" header="h1" call="#param_y" path="0:3:1:1:2" type="float" icon="y.png"/>
        <param tool_tip="Repeat" type="sub-header" call="#param_h5" name="Repeat" path="0:3:1:2"/>
        <param tool_tip="Number of copies" name="X axis copies" value="2" header="h5" call="#param_numx" path="0:3:1:2:0" icon="num.png" type="int" minimum_value="1"/>
        <param tool_tip="Number of copies" name="Y axis copies" value="3" header="h5" call="#param_numy" path="0:3:1:2:1" icon="num.png" type="int" minimum_value="1"/>
        <param tool_tip="Offsets" type="sub-header" call="#param_h2" name="Offsets" path="0:3:1:3"/>
        <param tool_tip="X step" name="dX" metric_value="30" value="100.000" header="h2" call="#param_dx" path="0:3:1:3:0" type="float" icon="dx.png"/>
        <param tool_tip="Y step" name="dY" metric_value="20" value="100.000" header="h2" call="#param_dy" path="0:3:1:3:1" type="float" icon="dy.png"/>
        <param tool_tip="Rotation" type="sub-header" call="#param_h3" name="Rotation" path="0:3:1:4"/>
        <param digits="2" tool_tip="Rotation of array" name="Rotation" value="20.00" header="h3" call="#param_r" path="0:3:1:4:0" type="float" icon="angle.png"/>
        <param tool_tip="System" type="sub-header" call="#param_h4" name="System" path="0:3:1:5"/>
        <param tool_tip="Use this coordinate system&#10;Returns to prior coordinate system afterward" name="Coordinate system" value="57" header="h4" call="#param_coord" path="0:3:1:5:0" type="combo" options="G55=55:G56=56:G57=57:G58=58:G59=59:G59.1=59.1:G59.2=59.2:G59.3=59.3"/>
        <param tool_tip="Items to copy" name="Items" old-selected="False" expanded="False" new-selected="False" call="#param_items" path="0:3:1:6" type="items" icon="items.png">
          <feature old-selected="False" src="/home/fernand/linuxcnc-features/ini/mill/fv_bolt-circle.ini" after="" help="&lt;b&gt;Create a regular circle&lt;/b&gt;" o-name="Drill Circle" before="" image="simp.png" expanded="False" id="drill-cir-001" new-selected="False" definitions="" call="&#10; &#9;(Drill a regular circle of #param_num holes)&#10;&#9;o&lt;#self_id&gt; if [#param_ena]&#10;&#9;&#9;#&lt;d&gt; = [#param_dim * #&lt;_units_r&gt;]&#10;&#9;&#9;o&lt;#self_id-10&gt; if [#param_opt] ; option diameter&#10;&#9;&#9;&#9;#&lt;#self_id-radius&gt; = [#&lt;d&gt; / 2 * #&lt;_units_r&gt;]&#10;&#9;&#9;o&lt;#self_id-10&gt; else ; option distance between holes&#10;&#9;&#9;&#9;o&lt;#self_id-10a&gt; if [[#param_ext MOD 360] EQ 0]&#10;&#9;&#9;&#9;&#9;#&lt;#self_id-radius&gt; = [#&lt;d&gt; / 2 / SIN[180 / #param_num]]&#10;&#9;&#9;&#9;o&lt;#self_id-10a&gt; else&#10;&#9;&#9;&#9;&#9;#&lt;#self_id-radius&gt; = [#&lt;d&gt; / SIN[#param_ext / #param_num]]&#10;&#9;&#9;&#9;o&lt;#self_id-10a&gt; endif&#10;&#9;&#9;o&lt;#self_id-10&gt; endif&#10;&#10;&#9;&#9;o&lt;#self_id-20&gt; if [[[#param_ext MOD 360] NE 0] AND [#param_num GT 1]]&#10;&#9;&#9;&#9;#&lt;#self_id-fill&gt; = [#param_ext * #param_num / [#param_num - 1]]&#10;&#9;&#9;o&lt;#self_id-20&gt; else&#10;&#9;&#9;&#9;#&lt;#self_id-fill&gt; = #param_ext&#10;&#9;&#9;o&lt;#self_id-20&gt; endif&#10;&#10;&#9;&#9;#&lt;i&gt; = 0&#10;&#9;&#9;o&lt;#self_id-loop&gt; while [#&lt;i&gt; LT #param_num]&#10;&#9; &#9;&#9;o&lt;rotate-xy&gt; CALL [#&lt;#self_id-radius&gt;] [0] [0] [0] [#param_a + [#&lt;#self_id-fill&gt; / #param_num] * #&lt;i&gt;]&#10;&#9;&#9;&#9;o&lt;fv_drill-one&gt; CALL [#param_cx + #&lt;_rotate_result_x&gt;] [#param_cy + #&lt;_rotate_result_y&gt;] [#param_depth] [#param_start]&#10;&#9;&#9;&#9;#&lt;i&gt; = [#&lt;i&gt; + 1]&#10;&#9;&#9;o&lt;#self_id-loop&gt; endwhile&#10;&#9;o&lt;#self_id&gt; endif&#10;" path="0:3:1:6:0" icon="tool.png" type="drill-cir" order="['PARAM_ENA', 'PARAM_H1', 'PARAM_CX', 'PARAM_CY', 'PARAM_OPT', 'PARAM_DIM', 'PARAM_H4', 'PARAM_NUM', 'PARAM_A', 'PARAM_EXT', 'PARAM_H3', 'PARAM_START', 'PARAM_DEPTH']" name="Drill Circle">
            <param tool_tip="Enabled" name="Enabled" value="1" call="#param_ena" path="0:3:1:6:0:0" type="bool"/>
            <param tool_tip="Coords, size" call="#param_h1" type="sub-header" name="Coords, size" path="0:3:1:6:0:1"/>
            <param tool_tip="Center of circle" name="cX" value="0.000" header="h1" call="#param_cx" path="0:3:1:6:0:1:0" type="float" icon="center.png"/>
            <param tool_tip="Center of circle" name="cY" value="0.000" header="h1" call="#param_cy" path="0:3:1:6:0:1:1" type="float" icon="center.png"/>
            <param tool_tip="Select dimension option" name="Measure by" value="0" header="h1" call="#param_opt" path="0:3:1:6:0:1:2" type="combo" options="Diameter=1:Distance between holes=0"/>
            <param tool_tip="Diameter or distance" name="Dimension" metric_value="50" value="50.000" header="h1" call="#param_dim" path="0:3:1:6:0:1:3" minimum_value="0.0" type="float" icon="diameter.png"/>
            <param tool_tip="Count, start, end" call="#param_h4" type="sub-header" name="Count, start, end" path="0:3:1:6:0:2"/>
            <param tool_tip="Number of holes" name="Number of holes" value="4" header="h4" call="#param_num" path="0:3:1:6:0:2:0" minimum_value="1" type="int" icon="num.png"/>
            <param digits="2" tool_tip="Angle of the first hole" name="Start" value="-45.00" header="h4" call="#param_a" path="0:3:1:6:0:2:1" type="float" icon="angle.png"/>
            <param digits="2" tool_tip="Angle covered by holes" name="Extend" value="360.00" header="h4" call="#param_ext" path="0:3:1:6:0:2:2" type="float" icon="angle.png"/>
            <param tool_tip="Drilling" call="#param_h3" type="sub-header" name="Drilling" path="0:3:1:6:0:3"/>
            <param tool_tip="Start drilling at height" name="Start drilling" metric_value="0" value="0.000" header="h3" call="#param_start" path="0:3:1:6:0:3:0" minimum_value="0.0" type="float" icon="surface.png"/>
            <param tool_tip="Depth of drilling" name="Drill depth" metric_value="-15" value="-15.000" header="h3" call="#param_depth" path="0:3:1:6:0:3:1" type="float" icon="dz.png"/>
          </feature>
        </param>
      </feature>
      <feature old-selected="False" src="/home/fernand/linuxcnc-features/ini/mill/fv_rectangular-array.ini" expanded="True" help="&lt;b&gt;Create a rectangular array of items&lt;/b&gt;" name="Array Rect" o-name="Array Rect" image="rect-array.png" after="&#10;&#9;&#9;&#9;(End array items)&#10;&#10;&#9;&#9;&#9;(No Angular increment in Y axis)&#10;&#9;&#9;&#9;#&lt;#self_id-Yy&gt; = [#&lt;#self_id-Yy&gt; + #param_dy]&#10;&#9;&#9;O&lt;#self_id-Y&gt; END REPEAT&#10;&#10;&#9;&#9;O&lt;coordinate-sys-to-num&gt; CALL [#param_coord]&#10;&#9;&#9;#&lt;coord&gt; = #&lt;_coordinate-to-num&gt;&#10;&#9;&#9;G10 L2 P[#&lt;Ycoord&gt;] X[#&lt;#self_id-Yx0&gt; - #param_x] Y[#&lt;#self_id-Yy0&gt; - #param_y] R[#&lt;#self_id-Yr0&gt;]&#10;&#9;&#9;O&lt;coordinate-sys-from-num&gt; CALL [#&lt;#self_id-Yrest-coord&gt;]&#10;&#9;&#9;G[#&lt;_coordinate-from-num&gt;]&#10;&#10;&#9;&#9;#&lt;#self_id-Xx&gt; = [#&lt;#self_id-Xx&gt; + #param_dx]&#10;&#9;O&lt;#self_id&gt; END REPEAT&#9;(End Y axis and return to main loop)&#10;&#10;&#9;O&lt;coordinate-sys-to-num&gt; CALL [#param_coord]&#10;&#9;#&lt;coord&gt; = #&lt;_coordinate-to-num&gt;&#10;&#9;G10 L2 P[#&lt;coord&gt;] X[#&lt;#self_id-Xx0&gt; - #param_x] Y[#&lt;#self_id-Xy0&gt; - #param_y] R[#&lt;#self_id-Xr0&gt; - #param_r]&#10;&#9;O&lt;coordinate-sys-from-num&gt; CALL [#&lt;#self_id-Xrest-coord&gt;]&#10;&#9;G[#&lt;_coordinate-from-num&gt;]&#10;O&lt;#self_id-enabled&gt; endif&#10;(End Rectangular Array)" order="['PARAM_ENA', 'PARAM_H1', 'PARAM_OPT', 'PARAM_X', 'PARAM_Y', 'PARAM_H5', 'PARAM_NUMX', 'PARAM_NUMY', 'PARAM_H2', 'PARAM_DX', 'PARAM_DY', 'PARAM_H3', 'PARAM_R', 'PARAM_H4', 'PARAM_COORD', 'PARAM_ITEMS']" new-selected="False" path="0:3:2" call="" definitions="" icon="rect-array.png" type="array-rect" id="array-rect-002" before="&#10;(Rectangular Array)&#10;O&lt;#self_id-enabled&gt; if [#param_ena]&#10;&#10;&#9;(Get x,y,r in machine coordinates)&#10;&#9;O&lt;#self_id-opt&gt; if [#param_opt EQ 1] ;center of array&#10;&#9;&#9;#&lt;#self_id-cx&gt; = [[#param_numx - 1] * #param_dx / 2]&#10;&#9;&#9;#&lt;#self_id-cy&gt; = [[#param_numy - 1] * #param_dy / 2]&#10;&#9;&#9;O&lt;#self_id-opt&gt; else ;align on low XY&#10;&#9;&#9;#&lt;#self_id-cx&gt; = 0&#10;&#9;&#9;#&lt;#self_id-cy&gt; = 0&#10;&#9;O&lt;#self_id-opt&gt; endif&#10;&#10;&#9;O&lt;get-offsets&gt; CALL&#10;&#9;#&lt;#self_id-Xx&gt; = 0&#10;&#10;&#9;#&lt;#self_id-Xx0&gt; = [#&lt;_get_offsets_x&gt; - #&lt;#self_id-cx&gt; + #param_x]&#10;&#9;#&lt;#self_id-Xy0&gt; = [#&lt;_get_offsets_y&gt; - #&lt;#self_id-cy&gt;]&#10;&#9;#&lt;#self_id-Xr0&gt; = [#&lt;_get_offsets_r&gt; + #param_r]&#10;&#10;&#9;#&lt;#self_id-Xrest-coord&gt; = #5220&#10;&#9;G[#param_coord]&#10;&#10;&#9;(Loop X axis)&#10;&#9;O&lt;#self_id&gt; REPEAT [#param_numx]&#10;&#10;&#9;&#9;G92.1 (disable G92 offsets - they ruin the array after rotating coordinates)&#10;&#9;&#9;(move and rotate coordinates)&#10;&#10;&#9;&#9;O&lt;coordinate-sys-to-num&gt; CALL [#param_coord]&#10;&#9;&#9;#&lt;#self_id-coord&gt; = #&lt;_coordinate-to-num&gt;&#10;&#10;&#9;&#9;(Get rotated coordinates)&#10;&#9;&#9;O&lt;rotate-xy&gt; CALL [#&lt;#self_id-Xx&gt; + #&lt;#self_id-Xx0&gt;] [#&lt;#self_id-Xy0&gt;] [#&lt;#self_id-Xx0&gt; + #&lt;#self_id-cx&gt;] [#&lt;#self_id-Xy0&gt; + #&lt;#self_id-cy&gt;] [#&lt;#self_id-Xr0&gt;]&#10;&#10;&#9;&#9;G10 L2 P[#&lt;#self_id-coord&gt;] X#&lt;_rotate_result_x&gt; Y#&lt;_rotate_result_y&gt; R[#&lt;#self_id-Xr0&gt;]&#10;&#10;&#9;&#9;(Array body Y axis)&#10;&#9;&#9;(Get x,y,r in machine coordinates)&#10;&#9;&#9;O&lt;get-offsets&gt; CALL&#10;&#9;&#9;#&lt;#self_id-Yy&gt; = [0]&#10;&#10;&#9;&#9;#&lt;#self_id-Yx0&gt; = [#&lt;_get_offsets_x&gt;]&#10;&#9;&#9;#&lt;#self_id-Yy0&gt; = [#&lt;_get_offsets_y&gt; + #param_y]&#10;&#9;&#9;#&lt;#self_id-Yr0&gt; = [#&lt;_get_offsets_r&gt;]&#10;&#9;&#9;#&lt;#self_id-Yrest-coord&gt; = #5220&#10;&#10;&#9;&#9;G[#param_coord]&#10;&#10;&#9;&#9;(Loop Y axis)&#10;&#9;&#9;O&lt;#self_id-Y&gt; REPEAT [#param_numy]&#10;&#10;&#9;&#9;&#9;G92.1 (disable G92 offsets - they ruin the array after rotating coordinates)&#10;&#9;&#9;&#9;(move and rotate coordinates)&#10;&#10;&#9;&#9;&#9;O&lt;coordinate-sys-to-num&gt; CALL [#param_coord]&#10;&#9;&#9;&#9;#&lt;Ycoord&gt; = #&lt;_coordinate-to-num&gt;&#10;&#10;&#9;&#9;&#9;(Get rotated coordinates)&#10;&#9;&#9;&#9;O&lt;rotate-xy&gt; CALL [#&lt;#self_id-Yx0&gt;] [#&lt;#self_id-Yy&gt; + #&lt;#self_id-Yy0&gt;] [#&lt;#self_id-Yx0&gt;] [#&lt;#self_id-Yy0&gt;] [#&lt;#self_id-Yr0&gt;]&#10;&#10;&#9;&#9;&#9;G10 L2 P[#&lt;Ycoord&gt;] X#&lt;_rotate_result_x&gt; Y#&lt;_rotate_result_y&gt; R[#&lt;#self_id-Yr0&gt;]&#10;&#10;&#9;&#9;&#9;(Array items ...)&#10;">
        <param tool_tip="Disabling will disable ALL items" name="Enabled" value="1" call="#param_ena" path="0:3:2:0" type="bool"/>
        <param tool_tip="Origin" type="sub-header" call="#param_h1" name="Coords" path="0:3:2:1"/>
        <param tool_tip="Select options" name="Position option" value="0" header="h1" call="#param_opt" path="0:3:2:1:0" type="combo" options="Low XY position=0:Center of array=1" icon="diameter.png"/>
        <param tool_tip="Origin X" name="X" value="0.000" header="h1" call="#param_x" path="0:3:2:1:1" type="float" icon="x.png"/>
        <param tool_tip="Origin Y" name="Y" value="0.000" header="h1" call="#param_y" path="0:3:2:1:2" type="float" icon="y.png"/>
        <param tool_tip="Repeat" type="sub-header" call="#param_h5" name="Repeat" path="0:3:2:2"/>
        <param tool_tip="Number of copies" name="X axis copies" value="2" header="h5" call="#param_numx" path="0:3:2:2:0" icon="num.png" type="int" minimum_value="1"/>
        <param tool_tip="Number of copies" name="Y axis copies" value="3" header="h5" call="#param_numy" path="0:3:2:2:1" icon="num.png" type="int" minimum_value="1"/>
        <param tool_tip="Offsets" type="sub-header" call="#param_h2" name="Offsets" path="0:3:2:3"/>
        <param tool_tip="X step" name="dX" metric_value="30" value="100.000" header="h2" call="#param_dx" path="0:3:2:3:0" type="float" icon="dx.png"/>
        <param tool_tip="Y step" name="dY" metric_value="20" value="100.000" header="h2" call="#param_dy" path="0:3:2:3:1" type="float" icon="dy.png"/>
        <param tool_tip="Rotation" type="sub-header" call="#param_h3" name="Rotation" path="0:3:2:4"/>
        <param digits="2" tool_tip="Rotation of array" name="Rotation" value="20.00" header="h3" call="#param_r" path="0:3:2:4:0" type="float" icon="angle.png"/>
        <param tool_tip="System" type="sub-header" call="#param_h4" name="System" path="0:3:2:5"/>
        <param tool_tip="Use this coordinate system&#10;Returns to prior coordinate system afterward" name="Coordinate system" value="57" header="h4" call="#param_coord" path="0:3:2:5:0" type="combo" options="G55=55:G56=56:G57=57:G58=58:G59=59:G59.1=59.1:G59.2=59.2:G59.3=59.3"/>
        <param tool_tip="Items to copy" name="Items" old-selected="False" expanded="True" new-selected="False" call="#param_items" path="0:3:2:6" type="items" icon="items.png">
          <feature src="/home/fernand/linuxcnc-features/ini/mill/fv_rect.ini" html_help="help/rectangles.html" after="" help="&lt;b&gt;Creates rectangle from center or corner&lt;/b&gt;&#10;Width / height may be negative&#10;Corners can be radiused or chamfered" old-selected="False" o-name="Rectangle 1 point" image="center-rect.png" expanded="False" id="rect-001" definitions="" new-selected="False" path="0:3:2:6:0" before="&#10;" call="&#10;&#9;o&lt;#self_id&gt; if [#param_ena]&#10;&#9;&#9;#&lt;w&gt;   = [#param_w * #&lt;_units_w&gt;]&#10;&#9;&#9;#&lt;h&gt;   = [#param_h * #&lt;_units_w&gt;]&#10;&#9;&#9;#&lt;cr&gt;  = [#param_cr * #&lt;_units_w&gt;]&#10;&#9;&#9;#&lt;dpt&gt; = [#param_dpt * #&lt;_units_d&gt;]&#10;&#9;&#9;o&lt;fv_rectangle&gt; CALL [#param_x] [#param_y] [#param_ref] [#&lt;w&gt;] [#&lt;h&gt;] [#param_rot] [#param_ct] [#&lt;cr&gt;] [#param_opt] [#param_dir] [#param_s] [#&lt;dpt&gt;] [#param_fc]&#10;&#9;o&lt;#self_id&gt; endif" icon="center-rect.png" type="rect" order="['PARAM_ENA', 'PARAM_H10', 'PARAM_REF', 'PARAM_X', 'PARAM_Y', 'PARAM_H11', 'PARAM_W', 'PARAM_H', 'PARAM_ROT', 'PARAM_H2', 'PARAM_CT', 'PARAM_CR', 'PARAM_H3', 'PARAM_OPT', 'PARAM_DIR', 'PARAM_S', 'PARAM_DPT', 'PARAM_FC']" name="Rectangle 1 point">
            <param tool_tip="Enabled" name="Enabled" value="1" call="#param_ena" path="0:3:2:6:0:0" type="bool"/>
            <param tool_tip="Coords" call="#param_h10" type="sub-header" name="Coords" path="0:3:2:6:0:1"/>
            <param tool_tip="Define reference point" name="Referenced by" value="1" header="h10" call="#param_ref" path="0:3:2:6:0:1:0" type="combo" options="One corner=0:Center of rectangle=1"/>
            <param tool_tip="Center or corner coord" name="cX or X" value="0.000" header="h10" call="#param_x" path="0:3:2:6:0:1:1" type="float" icon="center.png"/>
            <param tool_tip="Center or corner coord" name="cY or Y" value="0.000" header="h10" call="#param_y" path="0:3:2:6:0:1:2" type="float" icon="center.png"/>
            <param tool_tip="Size, rotation" call="#param_h11" type="sub-header" name="Size, rotation" path="0:3:2:6:0:2"/>
            <param tool_tip="Positive or negative value" name="Width" metric_value="75" value="75.000" header="h11" call="#param_w" path="0:3:2:6:0:2:0" type="float" icon="width.png"/>
            <param tool_tip="Positive or negative value" name="Height" metric_value="50" value="75.000" header="h11" call="#param_h" path="0:3:2:6:0:2:1" type="float" icon="height.png"/>
            <param digits="2" tool_tip="Angle rotated" name="Rotation" value="0.00" header="h11" call="#param_rot" path="0:3:2:6:0:2:2" type="float" icon="angle.png"/>
            <param tool_tip="Corners" call="#param_h2" type="sub-header" name="Corners" path="0:3:2:6:0:3"/>
            <param tool_tip="Select corner style" name="Style" value="0" header="h2" call="#param_ct" path="0:3:2:6:0:3:0" type="combo" options="None=0:Chamfer=1:Rounded=2:Inverted Round=3"/>
            <param tool_tip="Radius or chamfer distance from corner" name="Radius" value="0.000" header="h2" call="#param_cr" path="0:3:2:6:0:3:1" minimum_value="0.0" type="float" icon="corner-radius.png"/>
            <param tool_tip="Milling" call="#param_h3" type="sub-header" name="Milling" path="0:3:2:6:0:4"/>
            <param tool_tip="Select tool path" name="Option" value="0" header="h3" call="#param_opt" path="0:3:2:6:0:4:0" type="combo" options="Inside=0:Outside=1:On the line=2:Create a pocket=3" icon="g4x.png"/>
            <param tool_tip="Direction of path" name="Direction" value="2" header="h3" call="#param_dir" path="0:3:2:6:0:4:1" type="combo" options="Clockwise=2:Counter-Clockwise=3" icon="cw-ccw.png"/>
            <param tool_tip="Surface is usual" name="Cut start" value="#&lt;_surface&gt;" header="h3" call="#param_s" path="0:3:2:6:0:4:2" type="string" icon="surface.png"/>
            <param tool_tip="Must be lower then cut start" name="Cut down to" value="#&lt;_depth&gt;" header="h3" call="#param_dpt" path="0:3:2:6:0:4:3" type="string" icon="depth.png"/>
            <param tool_tip="Preview final cut" name="Preview final cut" value="1" header="h3" call="#param_fc" path="0:3:2:6:0:4:4" type="bool"/>
          </feature>
          <feature old-selected="False" src="/home/fernand/linuxcnc-features/ini/mill/fv_circle.ini" html_help="www.rds.ca" expanded="False" help="&lt;b&gt;Creates a circle&lt;/b&gt;&#10;Can also create a D shape" name="Circle 1 point" o-name="Circle 1 point" image="circle.png" after="" order="['PARAM_ENA', 'PARAM_H1', 'PARAM_CX', 'PARAM_CY', 'PARAM_D', 'PARAM_H2', 'PARAM_F', 'PARAM_ROT', 'PARAM_H3', 'PARAM_OPT', 'PARAM_DIR', 'PARAM_S', 'PARAM_DPT', 'PARAM_FCUT']" new-selected="False" call="&#10;&#9;o&lt;#self_id&gt; if [#param_ena]&#10;&#9;&#9;o&lt;fv_circle&gt; CALL [#param_cx][#param_cy][#param_d*#&lt;_units_r&gt;][#param_f*#&lt;_units_r&gt;] [#param_rot] [#param_opt] [#param_dir] [#param_s] [#param_dpt*#&lt;_units_d&gt;] [#param_fcut]&#10;&#9;o&lt;#self_id&gt; endif&#10;" path="0:3:2:6:1" definitions="" icon="circle.png" type="circle" id="circle-001" before="&#10;">
            <param tool_tip="Enabled" name="Enabled" value="1" call="#param_ena" path="0:3:2:6:1:0" type="bool"/>
            <param tool_tip="Coords, size" type="sub-header" call="#param_h1" name="Coords, size" path="0:3:2:6:1:1"/>
            <param tool_tip="Center of circle" name="cX" value="0.000" header="h1" call="#param_cx" path="0:3:2:6:1:1:0" type="float" icon="center.png"/>
            <param tool_tip="Center of circle" name="cY" value="0.000" header="h1" call="#param_cy" path="0:3:2:6:1:1:1" type="float" icon="center.png"/>
            <param tool_tip="Diameter" name="Diameter" metric_value="45" value="45.000" header="h1" call="#param_d" path="0:3:2:6:1:1:2" icon="diameter.png" type="float" minimum_value="0.0"/>
            <param tool_tip="D flat" type="sub-header" call="#param_h2" name="D flat" path="0:3:2:6:1:2"/>
            <param tool_tip="Height to remove from diameter" name="Remove" value="0.000" header="h2" call="#param_f" path="0:3:2:6:1:2:0" minimum_value="0.0" type="float" icon="d-flat.png"/>
            <param digits="2" tool_tip="Rotation of flat" name="Rotation" value="0.00" header="h2" call="#param_rot" path="0:3:2:6:1:2:1" type="float" icon="angle.png"/>
            <param tool_tip="Milling" type="sub-header" call="#param_h3" name="Milling" path="0:3:2:6:1:3"/>
            <param tool_tip="Select tool path" name="Option" value="0" header="h3" call="#param_opt" path="0:3:2:6:1:3:0" type="combo" options="Inside=0:Outside=1:On the line=2:Create a pocket=3" icon="g4x.png"/>
            <param tool_tip="Direction of path" name="Direction" value="2" header="h3" call="#param_dir" path="0:3:2:6:1:3:1" type="combo" options="Clockwise=2:Counter-Clockwise=3" icon="cw-ccw.png"/>
            <param tool_tip="Surface is usual" name="Cut start" value="#&lt;_surface&gt;" header="h3" call="#param_s" path="0:3:2:6:1:3:2" type="string" icon="surface.png"/>
            <param tool_tip="Must be lower then cut start" name="Cut down to" value="#&lt;_depth&gt;" header="h3" call="#param_dpt" path="0:3:2:6:1:3:3" type="string" icon="depth.png"/>
            <param tool_tip="Preview final cut" name="Preview final cut" value="1" header="h3" call="#param_fcut" path="0:3:2:6:1:3:4" type="bool"/>
          </feature>
        </param>
      </feature>
      <feature old-selected="False" src="/home/fernand/linuxcnc-features/ini/fv_tool-change.ini" expanded="False" help="&lt;b&gt;Add tool change gcode&lt;/b&gt;&#10;Changes setting accordingly even if disabled" name="Tool Change" o-name="Tool Change" image="tool-change.png" after="" order="['PARAM_ENA', 'PARAM_H1', 'PARAM_N', 'PARAM_STOP_COOLING', 'PARAM_COOLING', 'PARAM_SPINDLE_DIR', 'PARAM_H3', 'PARAM_H6', 'PARAM_SPEED', 'PARAM_F_SPEED', 'PARAM_H7', 'PARAM_FEED', 'PARAM_F_FEED', 'PARAM_V_FEED', 'PARAM_H5', 'PARAM_PEN', 'PARAM_STP', 'PARAM_PR', 'PARAM_PKR']" new-selected="False" path="0:3:3" call="&#10;(Tool change)&#10;o&lt;#self_id-ena&gt; if [#param_ena]&#10;&#9;o&lt;#self_id-stopcooling&gt; if [#param_stop_cooling]&#10;&#9;&#9;M9&#10;&#9;o&lt;#self_id-stopcooling&gt; endif&#10;&#9;T#param_n M6 G43&#10;&#10;&#9;o&lt;#self_id-if&gt; if [#&lt;_tool_probe_set&gt;]&#10;&#9;&#9;o&lt;set-tool-length&gt; CALL&#10;&#9;o&lt;#self_id-if&gt; endif&#10;&#10;&#9;M#param_spindle_dir&#10;&#9;M#param_cooling&#10;o&lt;#self_id-ena&gt; endif&#10;&#10;S#param_speed&#10;F#param_feed&#10;&#10;#&lt;_spindle_rpm&gt; = #param_speed&#10;#&lt;_final_feed&gt; = #param_f_feed&#10;#&lt;_final_spindle_rpm&gt; = #param_f_speed&#10;#&lt;_ffeed&gt; = #param_feed&#10;#&lt;_vertical_feed&gt; = #param_v_feed&#10;#&lt;_plunge_down&gt; = #param_pen&#10;#&lt;_depth_step&gt; = #param_stp&#10;#&lt;_plunge_ratio&gt; = #param_pr&#10;#&lt;_pocket_ratio&gt; = #param_pkr&#10;(End tool change)" definitions="" icon="tool-change.png" type="toolchng" id="toolchng-002" before="">
        <param tool_tip="Cutting params will be set even if disabled" name="Enabled" value="1" call="#param_ena" path="0:3:3:0" type="bool"/>
        <param tool_tip="Tool, execution" type="sub-header" call="#param_h1" name="Tool, execution" path="0:3:3:1"/>
        <param tool_tip="Tool number from table" name="Tool number" maximum_value="64" value="0" header="h1" call="#param_n" path="0:3:3:1:0" icon="num.png" type="int" minimum_value="0"/>
        <param tool_tip="Stop cooling before changing tool" name="Stop cooling" value="1" header="h1" call="#param_stop_cooling" path="0:3:3:1:1" type="bool" icon=""/>
        <param tool_tip="Use flood, mist or none" name="Re-start cooling" value="9" header="h1" call="#param_cooling" path="0:3:3:1:2" type="combo" options="None=9:Flood=8:Mist=7" icon=""/>
        <param tool_tip="Select tool rotation" name="Spindle direction" value="3" header="h1" call="#param_spindle_dir" path="0:3:3:1:3" type="combo" options="Clockwise=3:Counterclockwise=4" icon="cw-ccw.png"/>
        <param tool_tip="Milling" type="sub-header" call="#param_h3" name="Milling" path="0:3:3:2"/>
        <param tool_tip="Speed" name="Speed" header="h3" call="#param_h6" path="0:3:3:2:0" type="sub-header"/>
        <param tool_tip="Set spindle speed" name="Normal" value="1000" header="h6" call="#param_speed" path="0:3:3:2:0:0" icon="tool-spindle.png" type="int" minimum_value="100"/>
        <param tool_tip="Spindle speed for final loop" name="Final" value="1000" header="h6" call="#param_f_speed" path="0:3:3:2:0:1" icon="tool-final-spindle.png" type="int" minimum_value="100"/>
        <param tool_tip="Feed" name="Feed" header="h3" call="#param_h7" path="0:3:3:2:1" type="sub-header"/>
        <param tool_tip="Set XY feed" name="Normal" metric_value="100" value="100.000" header="h7" call="#param_feed" path="0:3:3:2:1:0" minimum_value="0.01" type="float" icon="tool-feed.png"/>
        <param tool_tip="Feed for last loop" name="Final" metric_value="75" value="75.000" header="h7" call="#param_f_feed" path="0:3:3:2:1:1" icon="tool-final-feed.png" type="float" minimum_value="0.1"/>
        <param tool_tip="Direct plunge feed when no XY move" name="Vertical" metric_value="20" value="20.000" header="h7" call="#param_v_feed" path="0:3:3:2:1:2" icon="tool-vertical-feed.png" type="float" minimum_value="0.1"/>
        <param tool_tip="Penetration" name="Penetration" header="h3" call="#param_h5" path="0:3:3:2:2" type="sub-header"/>
        <param tool_tip="How Z position is attained" name="Mode" value="0" header="h5" call="#param_pen" path="0:3:3:2:2:0" type="combo" options="Plunge to Z while moving to XY=0:Plunge to Z then go to XY=1"/>
        <param tool_tip="Step down on each pass" name="Cut step" metric_value="-3" maximum_value="-0.005" value="-3.000" header="h5" call="#param_stp" path="0:3:3:2:2:1" type="float" icon="depth.png"/>
        <param digits="2" tool_tip="Z versus XY move" name="Penetration ratio" maximum_value="1.0" value="0.07" header="h5" call="#param_pr" path="0:3:3:2:2:2" minimum_value="0.01" type="float" icon="tool-penetration-angle.png"/>
        <param digits="2" tool_tip="XY cut step versus tool diameter" name="Pocketing ratio" maximum_value="1.0" value="0.80" header="h5" call="#param_pkr" path="0:3:3:2:2:3" minimum_value="0.2" type="float" icon="rect-pocket.png"/>
      </feature>
    </param>
    <param tool_tip="Post Processing" name="Post Processing" old-selected="False" expanded="False" new-selected="False" call="#param_h2" path="0:4" type="header"/>
    <param tool_tip="Remove tool from spindle" name="Unmount tool" value="0" header="h2" call="#param_umnt" path="0:4:0" type="bool"/>
    <param tool_tip="Go to following position" name="Reset position to" value="0" header="h2" call="#param_sp" path="0:4:1" type="boolean"/>
    <param tool_tip="Go to at ending if checked" name="X" value="#&lt;_x&gt;" header="h2" call="#param_px" path="0:4:2" type="string" icon="x.png"/>
    <param tool_tip="Go to at ending if checked" name="Y" value="#&lt;_y&gt;" header="h2" call="#param_py" path="0:4:3" type="string" icon="y.png"/>
    <param tool_tip="Go to at ending if checked" name="Z" value="#&lt;_z&gt;" header="h2" call="#param_pz" path="0:4:4" type="string" icon="z.png"/>
  </feature>
</LinuxCNC-Features>
